{"_ts":[1501707367,1502055609,1502233561,1502401594],"_r":{"breakdown":{"html":{"bytes":[31497,31497,31497,31497],"requests":[2,2,2,2]},"js":{"bytes":[132003,132235,132189,132003],"requests":[10,10,10,10]},"css":{"bytes":[106751,106901,106751,106751],"requests":[6,6,6,6]},"image":{"bytes":[546006,546006,546006,546006],"requests":[42,42,42,42]},"flash":{"bytes":[0,0,0,0],"requests":[0,0,0,0]},"font":{"bytes":[62174,62174,62174,62174],"requests":[2,2,2,2]},"other":{"bytes":[0,0,0,0],"requests":[0,0,0,0]}},"date":[1501707367,1502055609,1502233561,1502401594],"domElements":[2038,2038,2038,2038],"domInteractive":[4423.2,4896.25,4011.8,4114.25],"firstPaint":[4085.4,4544.75,3696.8,3683.25],"fullyLoaded":[6329.6,6780.5,6177,5854.25],"id":["170802_N7_1J55","170806_JH_1A2H","170808_H9_20NP","170810_G9_23S1"],"loadTime":[6063.2,6529.5,5880.2,5584],"render":[4671.8,4926.5,3895.6,4006],"SpeedIndex":[5534.4,5806,4844.2,4904.25],"TTFB":[2233,2777.5,1811,1821.25],"videoFrames":[[{"_i":"frame_0000.jpg","_t":0,"_vc":0},{"_i":"frame_0044.jpg","_t":4400,"_vc":57},{"_i":"frame_0052.jpg","_t":5200,"_vc":79},{"_i":"frame_0055.jpg","_t":5500,"_vc":80},{"_i":"frame_0066.jpg","_t":6600,"_vc":81},{"_i":"frame_0067.jpg","_t":6700,"_vc":82},{"_i":"frame_0069.jpg","_t":6900,"_vc":86},{"_i":"frame_0070.jpg","_t":7000,"_vc":89},{"_i":"frame_0072.jpg","_t":7200,"_vc":100}],[{"_i":"frame_0000.jpg","_t":0,"_vc":0},{"_i":"frame_0047.jpg","_t":4700,"_vc":57},{"_i":"frame_0060.jpg","_t":6000,"_vc":79},{"_i":"frame_0068.jpg","_t":6800,"_vc":80},{"_i":"frame_0080.jpg","_t":8000,"_vc":83},{"_i":"frame_0081.jpg","_t":8100,"_vc":85},{"_i":"frame_0083.jpg","_t":8300,"_vc":98},{"_i":"frame_0085.jpg","_t":8500,"_vc":100}],[{"_i":"frame_0000.jpg","_t":0,"_vc":0},{"_i":"frame_0041.jpg","_t":4100,"_vc":67},{"_i":"frame_0049.jpg","_t":4900,"_vc":79},{"_i":"frame_0052.jpg","_t":5200,"_vc":79},{"_i":"frame_0054.jpg","_t":5400,"_vc":80},{"_i":"frame_0066.jpg","_t":6600,"_vc":81},{"_i":"frame_0068.jpg","_t":6800,"_vc":84},{"_i":"frame_0069.jpg","_t":6900,"_vc":86},{"_i":"frame_0070.jpg","_t":7000,"_vc":89},{"_i":"frame_0072.jpg","_t":7200,"_vc":100}],[{"_i":"frame_0000.jpg","_t":0,"_vc":0},{"_i":"frame_0045.jpg","_t":4500,"_vc":57},{"_i":"frame_0050.jpg","_t":5000,"_vc":79},{"_i":"frame_0055.jpg","_t":5500,"_vc":80},{"_i":"frame_0067.jpg","_t":6700,"_vc":82},{"_i":"frame_0068.jpg","_t":6800,"_vc":84},{"_i":"frame_0069.jpg","_t":6900,"_vc":86},{"_i":"frame_0071.jpg","_t":7100,"_vc":99},{"_i":"frame_0073.jpg","_t":7300,"_vc":100}]],"visualComplete":[7860,8275,7680,7450],"lighthouse":[null,null,null,null],"pagespeed":[70,67,68,72]}}