{"_ts":[1483274231],"_r":{"breakdown":{"html":{"bytes":[31648],"requests":[3]},"js":{"bytes":[129807],"requests":[9]},"css":{"bytes":[102620],"requests":[6]},"image":{"bytes":[644244],"requests":[37]},"flash":{"bytes":[0],"requests":[0]},"font":{"bytes":[62174],"requests":[2]},"other":{"bytes":[0],"requests":[0]}},"date":[1483274231],"domElements":[1851],"domInteractive":[7197.8],"firstPaint":[6933.2],"fullyLoaded":[9749.4],"id":["170101_9C_EDV"],"loadTime":[9624],"render":[7244.8],"SpeedIndex":[8307.2],"TTFB":[3972.2],"videoFrames":[[{"_t":0,"_vc":0},{"_t":5700,"_vc":62},{"_t":6500,"_vc":72},{"_t":7700,"_vc":74},{"_t":8700,"_vc":76},{"_t":8800,"_vc":78},{"_t":9000,"_vc":80},{"_t":9200,"_vc":100}]],"visualComplete":[11040.6]}}