{"_ts":[1530476259,1530649372,1530822995,1530995968,1531169433],"_r":{"breakdown":{"html":{"bytes":[24195,24195,24195,24195,24195],"requests":[3,3,3,3,3]},"js":{"bytes":[137697,139413,137688,137697,139997],"requests":[11,11,11,11,11]},"css":{"bytes":[106998,106998,106998,106998,106998],"requests":[5,5,5,5,5]},"image":{"bytes":[1172101,1172101,1172101,1172101,1172101],"requests":[59,59,59,59,59]},"flash":{"bytes":[0,0,0,0,0],"requests":[0,0,0,0,0]},"font":{"bytes":[62170,62170,62170,62170,62170],"requests":[2,2,2,2,2]},"video":{"bytes":[0,0,0,0,0],"requests":[0,0,0,0,0]},"other":{"bytes":[0,0,0,0,0],"requests":[0,0,0,0,0]}},"date":[1530476259,1530649372,1530822995,1530995968,1531169433],"domElements":[2062.6,2059.8,2062.6,2062.6,2062.6],"domInteractive":[5930,5948.2,6091,6074.2,5946.8],"firstPaint":[4830.6799999991,4782.2600000014,4802.9399999999,4817.1999999962,4718.7399999995],"fullyLoaded":[14423.2,14414,14438.6,14496,14280],"id":["180701_E0_58994f6405628ad3d04f5b1ce990db52","180703_R2_fbdde76988d094152654486907f5134f","180705_BB_65c679aff16250bf19191718bbc50084","180707_SG_9738f81148437681e37da9738455b59e","180709_EF_28d5ed8aff24b219a8161b81de91e8ea"],"loadTime":[13199.4,13139,13114,13179.6,12945.2],"render":[4880,4800,4840,4820,4800],"SpeedIndex":[8689.4,8590,8660.4,8645,8567],"TTFB":[2654.2,2743.8,2834.4,2716.8,2651.8],"videoFrames":[[{"_i":"ms_000000.jpg","_t":0,"_vc":0},{"_i":"ms_004500.jpg","_t":4500,"_vc":13},{"_i":"ms_004600.jpg","_t":4600,"_vc":68},{"_i":"ms_004800.jpg","_t":4800,"_vc":68},{"_i":"ms_004900.jpg","_t":4900,"_vc":68},{"_i":"ms_005000.jpg","_t":5000,"_vc":68},{"_i":"ms_005100.jpg","_t":5100,"_vc":67},{"_i":"ms_005200.jpg","_t":5200,"_vc":66},{"_i":"ms_006000.jpg","_t":6000,"_vc":9},{"_i":"ms_007000.jpg","_t":7000,"_vc":70},{"_i":"ms_007100.jpg","_t":7100,"_vc":69},{"_i":"ms_007200.jpg","_t":7200,"_vc":67},{"_i":"ms_007300.jpg","_t":7300,"_vc":67},{"_i":"ms_009700.jpg","_t":9700,"_vc":68},{"_i":"ms_010200.jpg","_t":10200,"_vc":67},{"_i":"ms_010300.jpg","_t":10300,"_vc":67},{"_i":"ms_010400.jpg","_t":10400,"_vc":68},{"_i":"ms_011000.jpg","_t":11000,"_vc":67},{"_i":"ms_011100.jpg","_t":11100,"_vc":67},{"_i":"ms_011400.jpg","_t":11400,"_vc":68},{"_i":"ms_012000.jpg","_t":12000,"_vc":67},{"_i":"ms_012100.jpg","_t":12100,"_vc":67},{"_i":"ms_012700.jpg","_t":12700,"_vc":67},{"_i":"ms_013000.jpg","_t":13000,"_vc":66},{"_i":"ms_013300.jpg","_t":13300,"_vc":67},{"_i":"ms_013700.jpg","_t":13700,"_vc":69},{"_i":"ms_013800.jpg","_t":13800,"_vc":70},{"_i":"ms_013900.jpg","_t":13900,"_vc":73},{"_i":"ms_014000.jpg","_t":14000,"_vc":76},{"_i":"ms_014100.jpg","_t":14100,"_vc":78},{"_i":"ms_014200.jpg","_t":14200,"_vc":80},{"_i":"ms_014300.jpg","_t":14300,"_vc":99},{"_i":"ms_014400.jpg","_t":14400,"_vc":100}],[{"_i":"ms_000000.jpg","_t":0,"_vc":0},{"_i":"ms_004900.jpg","_t":4900,"_vc":13},{"_i":"ms_005000.jpg","_t":5000,"_vc":68},{"_i":"ms_005100.jpg","_t":5100,"_vc":67},{"_i":"ms_005200.jpg","_t":5200,"_vc":67},{"_i":"ms_005300.jpg","_t":5300,"_vc":67},{"_i":"ms_005400.jpg","_t":5400,"_vc":67},{"_i":"ms_005500.jpg","_t":5500,"_vc":66},{"_i":"ms_006200.jpg","_t":6200,"_vc":9},{"_i":"ms_006300.jpg","_t":6300,"_vc":9},{"_i":"ms_006900.jpg","_t":6900,"_vc":9},{"_i":"ms_007000.jpg","_t":7000,"_vc":9},{"_i":"ms_007100.jpg","_t":7100,"_vc":9},{"_i":"ms_007300.jpg","_t":7300,"_vc":70},{"_i":"ms_007400.jpg","_t":7400,"_vc":67},{"_i":"ms_007500.jpg","_t":7500,"_vc":67},{"_i":"ms_007600.jpg","_t":7600,"_vc":67},{"_i":"ms_007700.jpg","_t":7700,"_vc":67},{"_i":"ms_009500.jpg","_t":9500,"_vc":67},{"_i":"ms_010000.jpg","_t":10000,"_vc":68},{"_i":"ms_010100.jpg","_t":10100,"_vc":67},{"_i":"ms_010200.jpg","_t":10200,"_vc":67},{"_i":"ms_011300.jpg","_t":11300,"_vc":67},{"_i":"ms_011800.jpg","_t":11800,"_vc":68},{"_i":"ms_011900.jpg","_t":11900,"_vc":67},{"_i":"ms_012000.jpg","_t":12000,"_vc":67},{"_i":"ms_013100.jpg","_t":13100,"_vc":67},{"_i":"ms_013400.jpg","_t":13400,"_vc":67},{"_i":"ms_014100.jpg","_t":14100,"_vc":68},{"_i":"ms_014200.jpg","_t":14200,"_vc":70},{"_i":"ms_014300.jpg","_t":14300,"_vc":73},{"_i":"ms_014400.jpg","_t":14400,"_vc":76},{"_i":"ms_014500.jpg","_t":14500,"_vc":78},{"_i":"ms_014600.jpg","_t":14600,"_vc":81},{"_i":"ms_014701.jpg","_t":14701,"_vc":81},{"_i":"ms_014800.jpg","_t":14800,"_vc":100}],[{"_i":"ms_000000.jpg","_t":0,"_vc":0},{"_i":"ms_004900.jpg","_t":4900,"_vc":68},{"_i":"ms_005100.jpg","_t":5100,"_vc":68},{"_i":"ms_005200.jpg","_t":5200,"_vc":68},{"_i":"ms_005300.jpg","_t":5300,"_vc":67},{"_i":"ms_005400.jpg","_t":5400,"_vc":66},{"_i":"ms_006300.jpg","_t":6300,"_vc":9},{"_i":"ms_007300.jpg","_t":7300,"_vc":67},{"_i":"ms_007400.jpg","_t":7400,"_vc":67},{"_i":"ms_007500.jpg","_t":7500,"_vc":67},{"_i":"ms_007700.jpg","_t":7700,"_vc":67},{"_i":"ms_009900.jpg","_t":9900,"_vc":68},{"_i":"ms_010700.jpg","_t":10700,"_vc":68},{"_i":"ms_010800.jpg","_t":10800,"_vc":67},{"_i":"ms_010900.jpg","_t":10900,"_vc":67},{"_i":"ms_011400.jpg","_t":11400,"_vc":68},{"_i":"ms_012000.jpg","_t":12000,"_vc":67},{"_i":"ms_012100.jpg","_t":12100,"_vc":67},{"_i":"ms_012600.jpg","_t":12600,"_vc":67},{"_i":"ms_013000.jpg","_t":13000,"_vc":66},{"_i":"ms_013300.jpg","_t":13300,"_vc":67},{"_i":"ms_014000.jpg","_t":14000,"_vc":69},{"_i":"ms_014100.jpg","_t":14100,"_vc":70},{"_i":"ms_014200.jpg","_t":14200,"_vc":73},{"_i":"ms_014300.jpg","_t":14300,"_vc":76},{"_i":"ms_014400.jpg","_t":14400,"_vc":77},{"_i":"ms_014500.jpg","_t":14500,"_vc":80},{"_i":"ms_014600.jpg","_t":14600,"_vc":99},{"_i":"ms_014701.jpg","_t":14701,"_vc":100}],[{"_i":"ms_000000.jpg","_t":0,"_vc":0},{"_i":"ms_004900.jpg","_t":4900,"_vc":13},{"_i":"ms_005000.jpg","_t":5000,"_vc":14},{"_i":"ms_005100.jpg","_t":5100,"_vc":68},{"_i":"ms_005200.jpg","_t":5200,"_vc":68},{"_i":"ms_005300.jpg","_t":5300,"_vc":68},{"_i":"ms_005400.jpg","_t":5400,"_vc":68},{"_i":"ms_005500.jpg","_t":5500,"_vc":68},{"_i":"ms_005800.jpg","_t":5800,"_vc":68},{"_i":"ms_005900.jpg","_t":5900,"_vc":67},{"_i":"ms_006000.jpg","_t":6000,"_vc":66},{"_i":"ms_006400.jpg","_t":6400,"_vc":9},{"_i":"ms_007500.jpg","_t":7500,"_vc":39},{"_i":"ms_007600.jpg","_t":7600,"_vc":67},{"_i":"ms_007700.jpg","_t":7700,"_vc":68},{"_i":"ms_007800.jpg","_t":7800,"_vc":67},{"_i":"ms_007900.jpg","_t":7900,"_vc":67},{"_i":"ms_011400.jpg","_t":11400,"_vc":68},{"_i":"ms_012000.jpg","_t":12000,"_vc":68},{"_i":"ms_012100.jpg","_t":12100,"_vc":67},{"_i":"ms_012200.jpg","_t":12200,"_vc":67},{"_i":"ms_013100.jpg","_t":13100,"_vc":67},{"_i":"ms_013500.jpg","_t":13500,"_vc":67},{"_i":"ms_014200.jpg","_t":14200,"_vc":68},{"_i":"ms_014300.jpg","_t":14300,"_vc":71},{"_i":"ms_014400.jpg","_t":14400,"_vc":74},{"_i":"ms_014500.jpg","_t":14500,"_vc":76},{"_i":"ms_014600.jpg","_t":14600,"_vc":77},{"_i":"ms_014701.jpg","_t":14701,"_vc":78},{"_i":"ms_014800.jpg","_t":14800,"_vc":98},{"_i":"ms_014900.jpg","_t":14900,"_vc":100}],[{"_i":"ms_000000.jpg","_t":0,"_vc":0},{"_i":"ms_004900.jpg","_t":4900,"_vc":13},{"_i":"ms_005000.jpg","_t":5000,"_vc":68},{"_i":"ms_005200.jpg","_t":5200,"_vc":68},{"_i":"ms_005300.jpg","_t":5300,"_vc":67},{"_i":"ms_005400.jpg","_t":5400,"_vc":67},{"_i":"ms_005500.jpg","_t":5500,"_vc":67},{"_i":"ms_005600.jpg","_t":5600,"_vc":67},{"_i":"ms_005700.jpg","_t":5700,"_vc":67},{"_i":"ms_005800.jpg","_t":5800,"_vc":66},{"_i":"ms_006100.jpg","_t":6100,"_vc":9},{"_i":"ms_006900.jpg","_t":6900,"_vc":70},{"_i":"ms_007000.jpg","_t":7000,"_vc":69},{"_i":"ms_007100.jpg","_t":7100,"_vc":67},{"_i":"ms_007200.jpg","_t":7200,"_vc":67},{"_i":"ms_007300.jpg","_t":7300,"_vc":67},{"_i":"ms_009900.jpg","_t":9900,"_vc":67},{"_i":"ms_010500.jpg","_t":10500,"_vc":67},{"_i":"ms_010600.jpg","_t":10600,"_vc":67},{"_i":"ms_011400.jpg","_t":11400,"_vc":67},{"_i":"ms_012000.jpg","_t":12000,"_vc":67},{"_i":"ms_012100.jpg","_t":12100,"_vc":67},{"_i":"ms_012700.jpg","_t":12700,"_vc":67},{"_i":"ms_013100.jpg","_t":13100,"_vc":67},{"_i":"ms_014200.jpg","_t":14200,"_vc":68},{"_i":"ms_014300.jpg","_t":14300,"_vc":70},{"_i":"ms_014400.jpg","_t":14400,"_vc":73},{"_i":"ms_014500.jpg","_t":14500,"_vc":76},{"_i":"ms_014600.jpg","_t":14600,"_vc":78},{"_i":"ms_014701.jpg","_t":14701,"_vc":80},{"_i":"ms_014800.jpg","_t":14800,"_vc":99},{"_i":"ms_014900.jpg","_t":14900,"_vc":100}]],"visualComplete":[14660,14560,14700.2,14720,14660],"lighthouse":[31,31,31,31,31],"pagespeed":[59,58,57,58,59]}}