{"_ts":[1559401945,1559575893,1559749614,1559921887,1560095480,1560268385],"_r":{"breakdown":{"html":{"bytes":[15294,15278,0,15305,15311,15311],"requests":[3,3,0,3,3,3]},"js":{"bytes":[118903,121003,0,119035,119035,119035],"requests":[8,8,0,8,8,8]},"css":{"bytes":[117019,115028,0,115231,115230,115286],"requests":[4,4,0,4,4,4]},"image":{"bytes":[264143,264143,0,264143,264143,264143],"requests":[24,24,0,24,24,24]},"flash":{"bytes":[0,0,0,0,0,0],"requests":[0,0,0,0,0,0]},"font":{"bytes":[61624,61624,0,61624,61624,61624],"requests":[2,2,0,2,2,2]},"video":{"bytes":[0,0,0,0,0,0],"requests":[0,0,0,0,0,0]},"other":{"bytes":[0,0,0,0,0,0],"requests":[0,0,1,0,0,0]}},"date":[1559401945,1559575893,1559749614,1559921887,1560095480,1560268385],"domElements":[1358,1358.4,null,1360.8,1361,1361],"domInteractive":[6446.6,6003.4,null,6288.2,7103.4,6004],"firstPaint":[6130.60000000298,5605.24099999966,null,5971.6540000009,6793.470999999221,5696.98799999806],"fullyLoaded":[9791.2,9285.4,null,10017.6,10688,9578],"id":["190601_MP_66ec4f2f6884c04a0740bf315a9ff3bc","190603_6Y_37fad58c8385b77a6df68e54e37c1417","190605_87_04fa63bd38d435b0205984c2bda1b976","190607_B8_635f625f54215dc2f2e1216e0e1a14bb","190609_06_c7027de7cc4f37b2bbf9bf9c4f2b96b2","190611_3E_32049ab2bda258f6a3f5a143545ef741"],"loadTime":[9391.2,8862.6,null,9617,10299.6,9184.2],"render":[6160,5660,null,6020,6840,5740],"SpeedIndex":[7885.4,7553,null,8336.2,9106.6,7941.2],"TTFB":[3992.4,3476.2,null,3760.6,4630,3463],"videoFrames":[[{"_i":"ms_000000.jpg","_t":0,"_vc":0},{"_i":"ms_005900.jpg","_t":5900,"_vc":29},{"_i":"ms_006000.jpg","_t":6000,"_vc":29},{"_i":"ms_006100.jpg","_t":6100,"_vc":29},{"_i":"ms_006300.jpg","_t":6300,"_vc":26},{"_i":"ms_006500.jpg","_t":6500,"_vc":26},{"_i":"ms_006700.jpg","_t":6700,"_vc":25},{"_i":"ms_006800.jpg","_t":6800,"_vc":24},{"_i":"ms_007000.jpg","_t":7000,"_vc":25},{"_i":"ms_007200.jpg","_t":7200,"_vc":28},{"_i":"ms_007300.jpg","_t":7300,"_vc":28},{"_i":"ms_007400.jpg","_t":7400,"_vc":28},{"_i":"ms_007500.jpg","_t":7500,"_vc":30},{"_i":"ms_007800.jpg","_t":7800,"_vc":69},{"_i":"ms_008200.jpg","_t":8200,"_vc":69},{"_i":"ms_008300.jpg","_t":8300,"_vc":69},{"_i":"ms_008400.jpg","_t":8400,"_vc":68},{"_i":"ms_008600.jpg","_t":8600,"_vc":69},{"_i":"ms_008700.jpg","_t":8700,"_vc":72},{"_i":"ms_008800.jpg","_t":8800,"_vc":75},{"_i":"ms_008900.jpg","_t":8900,"_vc":74},{"_i":"ms_009000.jpg","_t":9000,"_vc":76},{"_i":"ms_009100.jpg","_t":9100,"_vc":80},{"_i":"ms_009200.jpg","_t":9200,"_vc":97},{"_i":"ms_009300.jpg","_t":9300,"_vc":98},{"_i":"ms_009400.jpg","_t":9400,"_vc":100}],[{"_i":"ms_000000.jpg","_t":0,"_vc":0},{"_i":"ms_005900.jpg","_t":5900,"_vc":29},{"_i":"ms_006400.jpg","_t":6400,"_vc":29},{"_i":"ms_006500.jpg","_t":6500,"_vc":29},{"_i":"ms_006600.jpg","_t":6600,"_vc":29},{"_i":"ms_006700.jpg","_t":6700,"_vc":29},{"_i":"ms_006800.jpg","_t":6800,"_vc":25},{"_i":"ms_007100.jpg","_t":7100,"_vc":28},{"_i":"ms_007200.jpg","_t":7200,"_vc":28},{"_i":"ms_007300.jpg","_t":7300,"_vc":28},{"_i":"ms_007400.jpg","_t":7400,"_vc":28},{"_i":"ms_007500.jpg","_t":7500,"_vc":28},{"_i":"ms_007600.jpg","_t":7600,"_vc":30},{"_i":"ms_007700.jpg","_t":7700,"_vc":30},{"_i":"ms_007800.jpg","_t":7800,"_vc":34},{"_i":"ms_007900.jpg","_t":7900,"_vc":70},{"_i":"ms_008400.jpg","_t":8400,"_vc":70},{"_i":"ms_008500.jpg","_t":8500,"_vc":70},{"_i":"ms_008600.jpg","_t":8600,"_vc":69},{"_i":"ms_008700.jpg","_t":8700,"_vc":70},{"_i":"ms_008800.jpg","_t":8800,"_vc":76},{"_i":"ms_008900.jpg","_t":8900,"_vc":77},{"_i":"ms_009000.jpg","_t":9000,"_vc":78},{"_i":"ms_009100.jpg","_t":9100,"_vc":85},{"_i":"ms_009200.jpg","_t":9200,"_vc":88},{"_i":"ms_009300.jpg","_t":9300,"_vc":98},{"_i":"ms_009400.jpg","_t":9400,"_vc":100}],[{"_i":"ms_000000.jpg","_t":0,"_vc":100}],[{"_i":"ms_000000.jpg","_t":0,"_vc":0},{"_i":"ms_006000.jpg","_t":6000,"_vc":29},{"_i":"ms_006100.jpg","_t":6100,"_vc":29},{"_i":"ms_006400.jpg","_t":6400,"_vc":26},{"_i":"ms_006600.jpg","_t":6600,"_vc":26},{"_i":"ms_006700.jpg","_t":6700,"_vc":26},{"_i":"ms_006800.jpg","_t":6800,"_vc":25},{"_i":"ms_007000.jpg","_t":7000,"_vc":27},{"_i":"ms_007100.jpg","_t":7100,"_vc":27},{"_i":"ms_007200.jpg","_t":7200,"_vc":27},{"_i":"ms_007300.jpg","_t":7300,"_vc":27},{"_i":"ms_007400.jpg","_t":7400,"_vc":28},{"_i":"ms_007500.jpg","_t":7500,"_vc":30},{"_i":"ms_007700.jpg","_t":7700,"_vc":66},{"_i":"ms_007800.jpg","_t":7800,"_vc":70},{"_i":"ms_007900.jpg","_t":7900,"_vc":70},{"_i":"ms_008400.jpg","_t":8400,"_vc":70},{"_i":"ms_008500.jpg","_t":8500,"_vc":70},{"_i":"ms_008600.jpg","_t":8600,"_vc":69},{"_i":"ms_008700.jpg","_t":8700,"_vc":70},{"_i":"ms_009200.jpg","_t":9200,"_vc":70},{"_i":"ms_009300.jpg","_t":9300,"_vc":70},{"_i":"ms_009400.jpg","_t":9400,"_vc":69},{"_i":"ms_010501.jpg","_t":10501,"_vc":70},{"_i":"ms_010600.jpg","_t":10600,"_vc":76},{"_i":"ms_010700.jpg","_t":10700,"_vc":75},{"_i":"ms_010800.jpg","_t":10800,"_vc":80},{"_i":"ms_010900.jpg","_t":10900,"_vc":85},{"_i":"ms_011000.jpg","_t":11000,"_vc":87},{"_i":"ms_011100.jpg","_t":11100,"_vc":98},{"_i":"ms_011200.jpg","_t":11200,"_vc":100}],[{"_i":"ms_000000.jpg","_t":0,"_vc":0},{"_i":"ms_009700.jpg","_t":9700,"_vc":29},{"_i":"ms_009800.jpg","_t":9800,"_vc":29},{"_i":"ms_009900.jpg","_t":9900,"_vc":29},{"_i":"ms_010200.jpg","_t":10200,"_vc":26},{"_i":"ms_010400.jpg","_t":10400,"_vc":26},{"_i":"ms_010501.jpg","_t":10501,"_vc":26},{"_i":"ms_010600.jpg","_t":10600,"_vc":25},{"_i":"ms_010800.jpg","_t":10800,"_vc":27},{"_i":"ms_010900.jpg","_t":10900,"_vc":27},{"_i":"ms_011000.jpg","_t":11000,"_vc":27},{"_i":"ms_011100.jpg","_t":11100,"_vc":28},{"_i":"ms_011200.jpg","_t":11200,"_vc":28},{"_i":"ms_011300.jpg","_t":11300,"_vc":30},{"_i":"ms_011500.jpg","_t":11500,"_vc":66},{"_i":"ms_011600.jpg","_t":11600,"_vc":69},{"_i":"ms_011700.jpg","_t":11700,"_vc":69},{"_i":"ms_011800.jpg","_t":11800,"_vc":68},{"_i":"ms_012400.jpg","_t":12400,"_vc":69},{"_i":"ms_013000.jpg","_t":13000,"_vc":69},{"_i":"ms_013100.jpg","_t":13100,"_vc":68},{"_i":"ms_014200.jpg","_t":14200,"_vc":69},{"_i":"ms_014300.jpg","_t":14300,"_vc":75},{"_i":"ms_014400.jpg","_t":14400,"_vc":73},{"_i":"ms_014500.jpg","_t":14500,"_vc":78},{"_i":"ms_014600.jpg","_t":14600,"_vc":84},{"_i":"ms_014700.jpg","_t":14700,"_vc":87},{"_i":"ms_014800.jpg","_t":14800,"_vc":97},{"_i":"ms_014900.jpg","_t":14900,"_vc":100}],[{"_i":"ms_000000.jpg","_t":0,"_vc":0},{"_i":"ms_005900.jpg","_t":5900,"_vc":29},{"_i":"ms_006100.jpg","_t":6100,"_vc":29},{"_i":"ms_006300.jpg","_t":6300,"_vc":25},{"_i":"ms_006700.jpg","_t":6700,"_vc":25},{"_i":"ms_006900.jpg","_t":6900,"_vc":24},{"_i":"ms_007000.jpg","_t":7000,"_vc":25},{"_i":"ms_007100.jpg","_t":7100,"_vc":27},{"_i":"ms_007200.jpg","_t":7200,"_vc":28},{"_i":"ms_007300.jpg","_t":7300,"_vc":28},{"_i":"ms_007400.jpg","_t":7400,"_vc":30},{"_i":"ms_007500.jpg","_t":7500,"_vc":30},{"_i":"ms_007600.jpg","_t":7600,"_vc":70},{"_i":"ms_007700.jpg","_t":7700,"_vc":70},{"_i":"ms_008300.jpg","_t":8300,"_vc":70},{"_i":"ms_008400.jpg","_t":8400,"_vc":70},{"_i":"ms_008500.jpg","_t":8500,"_vc":70},{"_i":"ms_009000.jpg","_t":9000,"_vc":70},{"_i":"ms_009100.jpg","_t":9100,"_vc":70},{"_i":"ms_009200.jpg","_t":9200,"_vc":69},{"_i":"ms_010300.jpg","_t":10300,"_vc":70},{"_i":"ms_010400.jpg","_t":10400,"_vc":76},{"_i":"ms_010500.jpg","_t":10500,"_vc":75},{"_i":"ms_010600.jpg","_t":10600,"_vc":78},{"_i":"ms_010700.jpg","_t":10700,"_vc":85},{"_i":"ms_010800.jpg","_t":10800,"_vc":88},{"_i":"ms_010900.jpg","_t":10900,"_vc":99},{"_i":"ms_011000.jpg","_t":11000,"_vc":100}]],"visualComplete":[9540,9680,null,11300,11960,10840],"lighthouse":[59,59,null,59,59,59],"pagespeed":[71,73,73,72,85,74]}}