{
  "_ts": [1480680739],
  "_r": {
    "breakdown": {
      "html": {
        "bytes": [84880],
        "requests": [5]
      },
      "js": {
        "bytes": [114658],
        "requests": [7]
      },
      "css": {
        "bytes": [97017],
        "requests": [4]
      },
      "image": {
        "bytes": [32535],
        "requests": [8]
      },
      "flash": {
        "bytes": [0],
        "requests": [0]
      },
      "font": {
        "bytes": [0],
        "requests": [0]
      },
      "other": {
        "bytes": [0],
        "requests": [0]
      }
    },
    "date": [1480680739],
    "domElements": [1917],
    "domInteractive": [5001.8],
    "firstPaint": [4950.2],
    "fullyLoaded": [8595.8],
    "id": ["161202_47_JK2"],
    "loadTime": [7630.8],
    "render": [5068.2],
    "SpeedIndex": [7389.2],
    "TTFB": [2704.4],
    "videoFrames": [
      [{
        "_t": 0,
        "_vc": 0
      }, {
        "_t": 5400,
        "_vc": 9
      }, {
        "_t": 5700,
        "_vc": 40
      }, {
        "_t": 6300,
        "_vc": 41
      }, {
        "_t": 6700,
        "_vc": 54
      }, {
        "_t": 9200,
        "_vc": 59
      }, {
        "_t": 9400,
        "_vc": 62
      }, {
        "_t": 9600,
        "_vc": 98
      }, {
        "_t": 9700,
        "_vc": 100
      }],
      [{
        "_t": 0,
        "_vc": 0
      }, {
        "_t": 5000,
        "_vc": 4
      }, {
        "_t": 5200,
        "_vc": 9
      }, {
        "_t": 5800,
        "_vc": 40
      }, {
        "_t": 6400,
        "_vc": 54
      }, {
        "_t": 6600,
        "_vc": 54
      }, {
        "_t": 8800,
        "_vc": 59
      }, {
        "_t": 9000,
        "_vc": 62
      }, {
        "_t": 9100,
        "_vc": 64
      }, {
        "_t": 9200,
        "_vc": 97
      }, {
        "_t": 9300,
        "_vc": 100
      }]
    ],
    "visualComplete": [9444.2]
  }
}
