{"_ts":[1479119032],"_r":{"breakdown":{"html":{"bytes":[30513],"requests":[3]},"js":{"bytes":[130195],"requests":[9]},"css":{"bytes":[102852],"requests":[6]},"image":{"bytes":[514138],"requests":[40]},"flash":{"bytes":[0],"requests":[0]},"font":{"bytes":[62220],"requests":[2]},"other":{"bytes":[0],"requests":[0]}},"date":[1479119032],"domElements":[1743],"domInteractive":[5817.6],"firstPaint":[5784],"fullyLoaded":[11924.6],"id":["161114_BH_G3T"],"loadTime":[10869.8],"render":[5927.8],"SpeedIndex":[8378.2],"TTFB":[3290.6],"videoFrames":[[{"_t":0,"_vc":0},{"_t":6500,"_vc":3},{"_t":7100,"_vc":61},{"_t":7500,"_vc":67},{"_t":11400,"_vc":67},{"_t":12500,"_vc":65},{"_t":12700,"_vc":71},{"_t":12800,"_vc":74},{"_t":13000,"_vc":98},{"_t":13100,"_vc":100}]],"visualComplete":[12724.4]}}