{"_ts":[1520076001,1520252457,1520421671,1520595206,1520768707,1520941817],"_r":{"breakdown":{"html":{"bytes":[24441,24441,23196,23196,23196,23196],"requests":[2,2,2,2,2,2]},"js":{"bytes":[119440,119440,119845,119847,119845,119845],"requests":[8,8,8,8,8,8]},"css":{"bytes":[105368,105368,105368,105368,105287,105368],"requests":[4,4,4,4,4,4]},"image":{"bytes":[39518,39518,39510,39510,39510,39510],"requests":[10,10,10,10,10,10]},"flash":{"bytes":[0,0,0,0,0,0],"requests":[0,0,0,0,0,0]},"font":{"bytes":[62174,62174,62174,62174,62174,62174],"requests":[2,2,2,2,2,2]},"video":{"bytes":[0,0,0,0,0,0],"requests":[0,0,0,0,0,0]},"other":{"bytes":[0,0,0,0,0,0],"requests":[0,0,0,0,0,0]}},"date":[1520076001,1520252457,1520421671,1520595206,1520768707,1520941817],"domElements":[2346,2346,2347,2347,2347,2347],"domInteractive":[8883,7866.4,7946.2,9092,9621.2,9785.4],"firstPaint":[8601.8000000041,7636.0400000006,3577.0000000019,1002.4600000004,0,0],"fullyLoaded":[12215.4,11354.6,7659.4,6092.6,6074.2,6102.2],"id":["180303_58_9c185f9b072927bee0247f1b5ded30be","180305_9Y_8a086bcbbcdf05f666714603dcf3c1c7","180307_WC_5b121e70482ba882e77bd0d91e5bf6f5","180309_CY_4c3a7f0fc59fe9e23468ba896639abd1","180311_3Q_03a4ce8955e6674e3f16ba8033e0d5b0","180313_ZB_b2099d45347a119104392c744e0a1dbb"],"loadTime":[11117.8,10265,6572.2,4992.8,4971.6,5008.8],"render":[8620,7620,7660,9060,9580,9720],"SpeedIndex":[10654.6,9637,9505.8,10773.4,11277.4,11489],"TTFB":[6155.8,5143.6,5190,6514.8,7022.8,7153.2],"videoFrames":[[{"_i":"ms_000000.jpg","_t":0,"_vc":0},{"_i":"ms_010200.jpg","_t":10200,"_vc":6},{"_i":"ms_010300.jpg","_t":10300,"_vc":10},{"_i":"ms_010800.jpg","_t":10800,"_vc":13},{"_i":"ms_010900.jpg","_t":10900,"_vc":18},{"_i":"ms_011000.jpg","_t":11000,"_vc":39},{"_i":"ms_011200.jpg","_t":11200,"_vc":40},{"_i":"ms_011300.jpg","_t":11300,"_vc":40},{"_i":"ms_011500.jpg","_t":11500,"_vc":40},{"_i":"ms_011800.jpg","_t":11800,"_vc":40},{"_i":"ms_012500.jpg","_t":12500,"_vc":40},{"_i":"ms_012700.jpg","_t":12700,"_vc":41},{"_i":"ms_012800.jpg","_t":12800,"_vc":44},{"_i":"ms_012900.jpg","_t":12900,"_vc":45},{"_i":"ms_013000.jpg","_t":13000,"_vc":48},{"_i":"ms_013100.jpg","_t":13100,"_vc":49},{"_i":"ms_013200.jpg","_t":13200,"_vc":54},{"_i":"ms_013300.jpg","_t":13300,"_vc":98},{"_i":"ms_013400.jpg","_t":13400,"_vc":100}],[{"_i":"ms_000000.jpg","_t":0,"_vc":0},{"_i":"ms_005400.jpg","_t":5400,"_vc":6},{"_i":"ms_006100.jpg","_t":6100,"_vc":27},{"_i":"ms_006300.jpg","_t":6300,"_vc":39},{"_i":"ms_006700.jpg","_t":6700,"_vc":41},{"_i":"ms_007300.jpg","_t":7300,"_vc":41},{"_i":"ms_007500.jpg","_t":7500,"_vc":41},{"_i":"ms_007700.jpg","_t":7700,"_vc":41},{"_i":"ms_007900.jpg","_t":7900,"_vc":41},{"_i":"ms_008000.jpg","_t":8000,"_vc":44},{"_i":"ms_008100.jpg","_t":8100,"_vc":45},{"_i":"ms_008200.jpg","_t":8200,"_vc":47},{"_i":"ms_008300.jpg","_t":8300,"_vc":49},{"_i":"ms_008400.jpg","_t":8400,"_vc":50},{"_i":"ms_008500.jpg","_t":8500,"_vc":95},{"_i":"ms_008600.jpg","_t":8600,"_vc":96},{"_i":"ms_008700.jpg","_t":8700,"_vc":100}],[{"_i":"ms_000000.jpg","_t":0,"_vc":0},{"_i":"ms_005600.jpg","_t":5600,"_vc":41},{"_i":"ms_007000.jpg","_t":7000,"_vc":39},{"_i":"ms_007200.jpg","_t":7200,"_vc":39},{"_i":"ms_007300.jpg","_t":7300,"_vc":40},{"_i":"ms_007400.jpg","_t":7400,"_vc":41},{"_i":"ms_007600.jpg","_t":7600,"_vc":41},{"_i":"ms_007800.jpg","_t":7800,"_vc":41},{"_i":"ms_008000.jpg","_t":8000,"_vc":41},{"_i":"ms_008100.jpg","_t":8100,"_vc":44},{"_i":"ms_008200.jpg","_t":8200,"_vc":47},{"_i":"ms_008300.jpg","_t":8300,"_vc":48},{"_i":"ms_008400.jpg","_t":8400,"_vc":49},{"_i":"ms_008500.jpg","_t":8500,"_vc":50},{"_i":"ms_008600.jpg","_t":8600,"_vc":92},{"_i":"ms_008700.jpg","_t":8700,"_vc":94},{"_i":"ms_008800.jpg","_t":8800,"_vc":100}],[{"_i":"ms_000000.jpg","_t":0,"_vc":0},{"_i":"ms_005100.jpg","_t":5100,"_vc":38},{"_i":"ms_005300.jpg","_t":5300,"_vc":41},{"_i":"ms_005600.jpg","_t":5600,"_vc":41},{"_i":"ms_005700.jpg","_t":5700,"_vc":40},{"_i":"ms_005900.jpg","_t":5900,"_vc":41},{"_i":"ms_006300.jpg","_t":6300,"_vc":41},{"_i":"ms_006700.jpg","_t":6700,"_vc":41},{"_i":"ms_006800.jpg","_t":6800,"_vc":41},{"_i":"ms_007100.jpg","_t":7100,"_vc":41},{"_i":"ms_007300.jpg","_t":7300,"_vc":41},{"_i":"ms_007400.jpg","_t":7400,"_vc":44},{"_i":"ms_007500.jpg","_t":7500,"_vc":45},{"_i":"ms_007600.jpg","_t":7600,"_vc":47},{"_i":"ms_007700.jpg","_t":7700,"_vc":48},{"_i":"ms_007800.jpg","_t":7800,"_vc":50},{"_i":"ms_007900.jpg","_t":7900,"_vc":51},{"_i":"ms_008000.jpg","_t":8000,"_vc":93},{"_i":"ms_008100.jpg","_t":8100,"_vc":100}],[{"_i":"ms_000000.jpg","_t":0,"_vc":0},{"_i":"ms_008500.jpg","_t":8500,"_vc":39},{"_i":"ms_008700.jpg","_t":8700,"_vc":40},{"_i":"ms_009100.jpg","_t":9100,"_vc":40},{"_i":"ms_009200.jpg","_t":9200,"_vc":39},{"_i":"ms_009600.jpg","_t":9600,"_vc":41},{"_i":"ms_009800.jpg","_t":9800,"_vc":41},{"_i":"ms_010100.jpg","_t":10100,"_vc":41},{"_i":"ms_010600.jpg","_t":10600,"_vc":41},{"_i":"ms_010700.jpg","_t":10700,"_vc":43},{"_i":"ms_010800.jpg","_t":10800,"_vc":44},{"_i":"ms_010900.jpg","_t":10900,"_vc":47},{"_i":"ms_011000.jpg","_t":11000,"_vc":48},{"_i":"ms_011100.jpg","_t":11100,"_vc":50},{"_i":"ms_011200.jpg","_t":11200,"_vc":92},{"_i":"ms_011300.jpg","_t":11300,"_vc":96},{"_i":"ms_011400.jpg","_t":11400,"_vc":100}],[{"_i":"ms_000000.jpg","_t":0,"_vc":0},{"_i":"ms_011900.jpg","_t":11900,"_vc":38},{"_i":"ms_012100.jpg","_t":12100,"_vc":41},{"_i":"ms_012300.jpg","_t":12300,"_vc":41},{"_i":"ms_012400.jpg","_t":12400,"_vc":41},{"_i":"ms_012500.jpg","_t":12500,"_vc":40},{"_i":"ms_012600.jpg","_t":12600,"_vc":39},{"_i":"ms_013100.jpg","_t":13100,"_vc":40},{"_i":"ms_013200.jpg","_t":13200,"_vc":40},{"_i":"ms_013600.jpg","_t":13600,"_vc":40},{"_i":"ms_014600.jpg","_t":14600,"_vc":41},{"_i":"ms_014701.jpg","_t":14701,"_vc":45},{"_i":"ms_014800.jpg","_t":14800,"_vc":48},{"_i":"ms_014900.jpg","_t":14900,"_vc":48},{"_i":"ms_015000.jpg","_t":15000,"_vc":50},{"_i":"ms_015100.jpg","_t":15100,"_vc":54},{"_i":"ms_015200.jpg","_t":15200,"_vc":96},{"_i":"ms_015300.jpg","_t":15300,"_vc":100}]],"visualComplete":[11800,10800,10820,12140,12620,12900],"lighthouse":[45,45,54,54,54,45],"pagespeed":[71,64,64,67,77,66]}}