{"_ts":[1491130884],"_r":{"breakdown":{"html":{"bytes":[22844],"requests":[3]},"js":{"bytes":[135821],"requests":[10]},"css":{"bytes":[101312],"requests":[5]},"image":{"bytes":[537002],"requests":[32]},"flash":{"bytes":[0],"requests":[0]},"font":{"bytes":[62174],"requests":[2]},"other":{"bytes":[0],"requests":[0]}},"date":[1491130884],"domElements":[1025],"domInteractive":[4925],"firstPaint":[5055],"fullyLoaded":[10625.4],"id":["170402_4J_GMV"],"loadTime":[9501.2],"render":[5165.6],"SpeedIndex":[7459.4],"TTFB":[2618.4],"videoFrames":[[{"_t":0,"_vc":0},{"_t":5100,"_vc":5},{"_t":5800,"_vc":67},{"_t":5900,"_vc":67},{"_t":6100,"_vc":70},{"_t":6700,"_vc":71},{"_t":6900,"_vc":71},{"_t":9700,"_vc":72},{"_t":10600,"_vc":73},{"_t":10700,"_vc":72},{"_t":10900,"_vc":76},{"_t":11000,"_vc":81},{"_t":11200,"_vc":100}]],"visualComplete":[11360],"pagespeed":[73]}}