{"_ts":[1546431506,1546608412,1546778156,1546947791],"_r":{"breakdown":{"html":{"bytes":[29575,29574,29575,28486],"requests":[2,2,2,2]},"js":{"bytes":[137482,137482,137473,134192],"requests":[10,10,10,10]},"css":{"bytes":[118970,118975,118969,116718],"requests":[5,5,5,5]},"image":{"bytes":[642806,642806,642806,625428],"requests":[45,45,45,45]},"flash":{"bytes":[0,0,0,0],"requests":[0,0,0,0]},"font":{"bytes":[62266,62266,62266,61624],"requests":[2,2,2,2]},"video":{"bytes":[0,0,0,0],"requests":[0,0,0,0]},"other":{"bytes":[0,0,0,0],"requests":[0,0,0,0]}},"date":[1546431506,1546608412,1546778156,1546947791],"domElements":[2250,2250,2250,2250],"domInteractive":[7092.8,6911.4,22345.75,6816.8],"firstPaint":[6287.5400000019,6245.6600000034,21638.924999995674,6222.65999999654],"fullyLoaded":[12446.8,12187.6,27573.25,12009.2],"id":["190102_MF_15c9348301c6158ffe8953b80c338c07","190104_HF_bf612188fec956fe536a724f1b6d202d","190106_W6_2009e0194cc2de81bc374ca970350fbf","190108_HM_017d918f21d51b34b137ae102db64346"],"loadTime":[11248.4,10973.2,26405.75,10807],"render":[6320,6260,21700,6280],"SpeedIndex":[9590.4,9419,24836.75,9416.6],"TTFB":[3731,3541.4,18738.5,3423.4],"videoFrames":[[{"_i":"ms_000000.jpg","_t":0,"_vc":0},{"_i":"ms_006800.jpg","_t":6800,"_vc":42},{"_i":"ms_006900.jpg","_t":6900,"_vc":42},{"_i":"ms_007100.jpg","_t":7100,"_vc":42},{"_i":"ms_007200.jpg","_t":7200,"_vc":42},{"_i":"ms_007300.jpg","_t":7300,"_vc":42},{"_i":"ms_007400.jpg","_t":7400,"_vc":42},{"_i":"ms_007500.jpg","_t":7500,"_vc":41},{"_i":"ms_007800.jpg","_t":7800,"_vc":42},{"_i":"ms_007900.jpg","_t":7900,"_vc":44},{"_i":"ms_008500.jpg","_t":8500,"_vc":44},{"_i":"ms_008600.jpg","_t":8600,"_vc":44},{"_i":"ms_008700.jpg","_t":8700,"_vc":44},{"_i":"ms_010000.jpg","_t":10000,"_vc":44},{"_i":"ms_011100.jpg","_t":11100,"_vc":44},{"_i":"ms_011200.jpg","_t":11200,"_vc":44},{"_i":"ms_011400.jpg","_t":11400,"_vc":44},{"_i":"ms_012000.jpg","_t":12000,"_vc":45},{"_i":"ms_012100.jpg","_t":12100,"_vc":48},{"_i":"ms_012200.jpg","_t":12200,"_vc":50},{"_i":"ms_012300.jpg","_t":12300,"_vc":55},{"_i":"ms_012400.jpg","_t":12400,"_vc":57},{"_i":"ms_012500.jpg","_t":12500,"_vc":60},{"_i":"ms_012600.jpg","_t":12600,"_vc":99},{"_i":"ms_012700.jpg","_t":12700,"_vc":100}],[{"_i":"ms_000000.jpg","_t":0,"_vc":0},{"_i":"ms_006200.jpg","_t":6200,"_vc":43},{"_i":"ms_006300.jpg","_t":6300,"_vc":43},{"_i":"ms_006400.jpg","_t":6400,"_vc":41},{"_i":"ms_006500.jpg","_t":6500,"_vc":41},{"_i":"ms_006600.jpg","_t":6600,"_vc":41},{"_i":"ms_006700.jpg","_t":6700,"_vc":41},{"_i":"ms_006800.jpg","_t":6800,"_vc":41},{"_i":"ms_007200.jpg","_t":7200,"_vc":42},{"_i":"ms_007400.jpg","_t":7400,"_vc":44},{"_i":"ms_007700.jpg","_t":7700,"_vc":44},{"_i":"ms_007800.jpg","_t":7800,"_vc":44},{"_i":"ms_007900.jpg","_t":7900,"_vc":44},{"_i":"ms_009700.jpg","_t":9700,"_vc":44},{"_i":"ms_010600.jpg","_t":10600,"_vc":44},{"_i":"ms_010701.jpg","_t":10701,"_vc":44},{"_i":"ms_010900.jpg","_t":10900,"_vc":45},{"_i":"ms_011000.jpg","_t":11000,"_vc":45},{"_i":"ms_011300.jpg","_t":11300,"_vc":46},{"_i":"ms_011400.jpg","_t":11400,"_vc":48},{"_i":"ms_011500.jpg","_t":11500,"_vc":50},{"_i":"ms_011600.jpg","_t":11600,"_vc":53},{"_i":"ms_011700.jpg","_t":11700,"_vc":54},{"_i":"ms_011800.jpg","_t":11800,"_vc":58},{"_i":"ms_011900.jpg","_t":11900,"_vc":97},{"_i":"ms_012000.jpg","_t":12000,"_vc":100}],[{"_i":"ms_000000.jpg","_t":0,"_vc":0},{"_i":"ms_022500.jpg","_t":22500,"_vc":42},{"_i":"ms_022600.jpg","_t":22600,"_vc":42},{"_i":"ms_022800.jpg","_t":22800,"_vc":42},{"_i":"ms_022900.jpg","_t":22900,"_vc":43},{"_i":"ms_023000.jpg","_t":23000,"_vc":43},{"_i":"ms_023100.jpg","_t":23100,"_vc":41},{"_i":"ms_023200.jpg","_t":23200,"_vc":42},{"_i":"ms_023700.jpg","_t":23700,"_vc":44},{"_i":"ms_024300.jpg","_t":24300,"_vc":44},{"_i":"ms_024400.jpg","_t":24400,"_vc":44},{"_i":"ms_024500.jpg","_t":24500,"_vc":44},{"_i":"ms_026300.jpg","_t":26300,"_vc":44},{"_i":"ms_026801.jpg","_t":26801,"_vc":44},{"_i":"ms_026900.jpg","_t":26900,"_vc":44},{"_i":"ms_027000.jpg","_t":27000,"_vc":44},{"_i":"ms_027100.jpg","_t":27100,"_vc":44},{"_i":"ms_027700.jpg","_t":27700,"_vc":45},{"_i":"ms_027800.jpg","_t":27800,"_vc":48},{"_i":"ms_027900.jpg","_t":27900,"_vc":52},{"_i":"ms_028000.jpg","_t":28000,"_vc":54},{"_i":"ms_028100.jpg","_t":28100,"_vc":57},{"_i":"ms_028200.jpg","_t":28200,"_vc":59},{"_i":"ms_028300.jpg","_t":28300,"_vc":98},{"_i":"ms_028400.jpg","_t":28400,"_vc":100}],[{"_i":"ms_000000.jpg","_t":0,"_vc":0},{"_i":"ms_006800.jpg","_t":6800,"_vc":42},{"_i":"ms_007100.jpg","_t":7100,"_vc":43},{"_i":"ms_007200.jpg","_t":7200,"_vc":44},{"_i":"ms_007300.jpg","_t":7300,"_vc":44},{"_i":"ms_007700.jpg","_t":7700,"_vc":44},{"_i":"ms_008000.jpg","_t":8000,"_vc":44},{"_i":"ms_008700.jpg","_t":8700,"_vc":44},{"_i":"ms_008800.jpg","_t":8800,"_vc":44},{"_i":"ms_008900.jpg","_t":8900,"_vc":44},{"_i":"ms_009000.jpg","_t":9000,"_vc":44},{"_i":"ms_010500.jpg","_t":10500,"_vc":44},{"_i":"ms_011000.jpg","_t":11000,"_vc":44},{"_i":"ms_011100.jpg","_t":11100,"_vc":44},{"_i":"ms_011200.jpg","_t":11200,"_vc":44},{"_i":"ms_011300.jpg","_t":11300,"_vc":44},{"_i":"ms_011800.jpg","_t":11800,"_vc":45},{"_i":"ms_011900.jpg","_t":11900,"_vc":48},{"_i":"ms_012000.jpg","_t":12000,"_vc":50},{"_i":"ms_012100.jpg","_t":12100,"_vc":55},{"_i":"ms_012200.jpg","_t":12200,"_vc":57},{"_i":"ms_012300.jpg","_t":12300,"_vc":59},{"_i":"ms_012400.jpg","_t":12400,"_vc":99},{"_i":"ms_012500.jpg","_t":12500,"_vc":100}]],"visualComplete":[12300,12060,27475,12040],"lighthouse":[57,57,57,57],"pagespeed":[60,60,59,62]}}